{
	"당신": 2,
	"완료": 1,
	"저장": 2,
	"게임": 8,
	"통해": 1,
	"절반": 1,
	"방법": 2,
	"경우": 1,
	"업데이트": 7,
	"로": 1,
	"모든": 7,
	"설정": 2,
	"데이터": 1,
	"손실": 1,
	"재": 1,
	"및": 1,
	"기능": 2,
	"본질": 1,
	"무료": 1,
	"의": 2,
	"사용자": 3,
	"그것": 1,
	"수": 8,
	"출시": 1,
	"것": 3,
	"이": 1,
	"응용": 1,
	"프로그램": 1,
	"앱": 1,
	"구매": 1,
	"전체": 2,
	"자신": 2,
	"스포츠": 1,
	"팀": 3,
	"추격": 1,
	"승리": 2,
	"제어": 2,
	"가라": 1,
	"편집": 1,
	"선수": 12,
	"이름": 2,
	"등급": 1,
	"경험": 2,
	"정의": 1,
	"로그인": 2,
	"거래": 1,
	"확인": 2,
	"기금": 1,
	"픽업": 1,
	"상기": 1,
	"드래프트": 1,
	"스타": 1,
	"훈련": 1,
	"업그레이드": 2,
	"방식": 1,
	"변경": 1,
	"시설": 1,
	"상품": 1,
	"판매": 1,
	"투자": 1,
	"헤드": 1,
	"코치": 2,
	"보조": 1,
	"은": 1,
	"플레이어": 4,
	"개발": 1,
	"데": 1,
	"도움": 1,
	"스카우트": 2,
	"재능": 1,
	"발견": 1,
	"트랙": 1,
	"매년": 1,
	"통계": 4,
	"경력": 1,
	"최고": 1,
	"더": 3,
	"별": 1,
	"올해": 1,
	"신인": 3,
	"등": 1,
	"도시": 1,
	"세계": 1,
	"제이": 1,
	"포함": 3,
	"명단": 1,
	"곧": 1,
	"재생": 1,
	"모드": 1,
	"상자": 1,
	"점수": 1,
	"놀이": 2,
	"사이": 1,
	"전환": 1,
	"의지": 1,
	"대한": 2,
	"제안": 1,
	"철회": 1,
	"이제": 1,
	"지도자": 1,
	"목록": 1,
	"볼": 1,
	"특색": 1,
	"명예": 2,
	"쇼": 1,
	"조랑말": 1,
	"미래": 1,
	"홀": 1,
	"지금": 2,
	"추적": 1,
	"추가": 1,
	"은퇴": 1,
	"때": 1,
	"전당": 1,
	"통": 1,
	"버튼": 2,
	"의도": 2,
	"인": 2,
	"파": 2,
	"울": 2,
	"보고": 1,
	"시간": 3,
	"관리": 1,
	"활용": 1,
	"해결": 1,
	"문제": 1,
	"일부": 1,
	"슬라이드": 1,
	"메뉴": 1,
	"계절": 1,
	"끝": 1,
	"제거": 1,
	"옆": 1,
	"플레이": 1,
	"소개": 1,
	"호출": 1,
	"마지막": 1,
	"촬영": 2,
	"공": 1,
	"총": 1,
	"시계": 1,
	"실행": 1,
	"선택": 1,
	"거나": 1,
	"나은": 1,
	"영감": 1,
	"피로": 1,
	"파일": 1,
	"로고": 1,
	"능력": 1
}