{
	"새": 1,
	"환상": 1,
	"멀티플레이": 1,
	"온라인": 1,
	"골프": 11,
	"게임": 6,
	"글로벌": 2,
	"오신": 1,
	"것": 1,
	"환영": 1,
	"실시간": 2,
	"경기": 5,
	"리얼": 1,
	"프로": 1,
	"장비": 1,
	"사용": 1,
	"능력": 1,
	"향상": 2,
	"수": 6,
	"게다가": 1,
	"그래픽": 2,
	"장면": 1,
	"통해": 3,
	"몰입": 3,
	"감": 1,
	"체험": 1,
	"지금": 1,
	"바로": 1,
	"다운로드": 2,
	"전": 4,
	"세계": 5,
	"플레이어": 6,
	"시합": 1,
	"누구": 1,
	"시작": 1,
	"남녀": 1,
	"노소": 1,
	"모든": 1,
	"초보자": 1,
	"위": 1,
	"가이드": 1,
	"제공": 1,
	"작법": 1,
	"터치": 1,
	"방식": 1,
	"골프채": 2,
	"스윙": 1,
	"정밀": 1,
	"조준": 2,
	"장치": 1,
	"슈팅": 1,
	"토너먼트": 2,
	"모드": 1,
	"수천": 1,
	"명의": 1,
	"접속": 1,
	"진행": 2,
	"언제": 1,
	"최고": 3,
	"추가": 1,
	"시스템": 1,
	"챔피언": 1,
	"여러분": 3,
	"꿈": 1,
	"실현": 1,
	"리그": 1,
	"랭킹": 1,
	"목록": 1,
	"선수": 1,
	"도전": 1,
	"실력": 2,
	"테스트": 1,
	"보상": 1,
	"코스": 3,
	"레벨": 1,
	"만족": 1,
	"승리": 2,
	"상금": 1,
	"공": 1,
	"업그레이드": 1,
	"위해": 1,
	"오픈": 1,
	"스테이지": 1,
	"경험": 2,
	"하이엔드": 1,
	"작동": 1,
	"선사": 1,
	"스타일": 1,
	"생동감": 1,
	"선택": 1,
	"시각": 1,
	"효과": 2,
	"음향": 1,
	"흥미진진": 1,
	"타임": 1,
	"킬러": 1,
	"라이벌": 2,
	"페이스북": 1,
	"친구": 3,
	"초대": 1,
	"플레이": 1,
	"반대": 1,
	"로부터": 1,
	"선물": 1,
	"다른": 1,
	"프로필": 1,
	"업로드": 1,
	"공유": 1,
	"대결": 1,
	"참가": 1,
	"경쟁": 1,
	"마스터": 1,
	"더": 1,
	"일": 1,
	"문의사항": 1,
	"의견": 1,
	"문의": 1
}