{
	"중요": 1,
	"를": 3,
	"응용": 8,
	"프로그램": 8,
	"작동": 1,
	"경우": 2,
	"방금": 1,
	"구글": 2,
	"텍스트": 1,
	"연설": 1,
	"엔진": 1,
	"재생": 1,
	"설치": 2,
	"대해": 2,
	"프로젝트": 2,
	"교육": 4,
	"당신": 7,
	"훈련": 2,
	"데": 2,
	"도움": 1,
	"만": 1,
	"설정": 2,
	"시행": 1,
	"성공": 1,
	"다른": 1,
	"사용": 3,
	"수": 7,
	"앱": 1,
	"말": 2,
	"때": 1,
	"이이": 1,
	"상관": 1,
	"하드": 2,
	"손가락": 2,
	"초": 2,
	"동안": 1,
	"정지": 1,
	"보유": 3,
	"주머니": 1,
	"어디": 1,
	"휴식": 2,
	"얼마나": 2,
	"시리즈": 6,
	"등": 1,
	"필요": 1,
	"행사": 2,
	"안드로이드": 1,
	"데이터": 1,
	"영어": 1,
	"폴란드어": 1,
	"언어": 1,
	"음성": 1,
	"명령": 1,
	"제공": 1,
	"맞춤": 1,
	"편집": 3,
	"위해": 2,
	"구현": 1,
	"또한": 2,
	"수동": 1,
	"매우": 1,
	"파일": 1,
	"카드": 1,
	"가능성": 1,
	"방법": 1,
	"수정": 1,
	"운동": 3,
	"전": 1,
	"소리": 1,
	"몇": 1,
	"사용자": 2,
	"정의": 2,
	"설명": 2,
	"삽입": 2,
	"친구": 1,
	"일부": 1,
	"메시지": 1,
	"공유": 1,
	"예": 1,
	"및": 5,
	"종류": 1,
	"안녕": 1,
	"스티브": 1,
	"관리": 1,
	"이름": 1,
	"절곡": 1,
	"암": 1,
	"지속": 1,
	"시간": 2,
	"수납": 2,
	"기간": 2,
	"나머지": 1,
	"제외": 1,
	"번호": 1,
	"사이": 1,
	"보류": 1,
	"첫": 1,
	"숫자": 1,
	"로우": 1,
	"두": 1,
	"번": 1,
	"열": 1,
	"인": 1,
	"이": 3,
	"주전자": 1,
	"저자": 1,
	"나": 3,
	"작성": 1,
	"고용": 1,
	"그": 1,
	"단지": 1,
	"자신": 1,
	"요구": 1,
	"더욱": 1,
	"발전": 1,
	"것": 1,
	"기능": 1,
	"추가": 1,
	"모든": 2,
	"사람": 2,
	"위": 1,
	"최선": 1,
	"니": 1,
	"이제": 1,
	"결정": 1
}