{
	"단지": 2,
	"어린이": 1,
	"성인": 1,
	"중": 2,
	"그룹": 3,
	"구성": 3,
	"것": 2,
	"당신": 3,
	"이벤트": 5,
	"공유": 2,
	"게시": 1,
	"물": 1,
	"사진": 2,
	"초대": 2,
	"수": 6,
	"하나": 1,
	"이메일": 2,
	"앱": 1,
	"통해": 1,
	"초대장": 3,
	"발송": 1,
	"처리": 1,
	"전체": 1,
	"개요": 2,
	"제공": 1,
	"위해": 1,
	"모든": 2,
	"해답": 1,
	"를": 3,
	"수집": 1,
	"사람": 3,
	"응답": 3,
	"응용": 1,
	"프로그램": 1,
	"우리": 2,
	"알림": 1,
	"부모": 1,
	"자녀": 1,
	"대신": 2,
	"대답": 1,
	"하위": 1,
	"엑셀": 1,
	"오기": 1,
	"회원": 1,
	"목록": 2,
	"반복": 1,
	"작성": 1,
	"여러": 3,
	"예약": 1,
	"글": 1,
	"정보": 1,
	"업데이트": 1,
	"대한": 2,
	"참가자": 1,
	"수출": 1,
	"날짜": 1,
	"제안": 1,
	"투표": 1,
	"사용자": 1,
	"캘린더": 1,
	"통합": 1,
	"추가": 1,
	"무료": 1
}