{
	"자라": 5,
	"숲속": 1,
	"동물": 6,
	"은": 1,
	"우리": 7,
	"자장가": 2,
	"이야기": 2,
	"시리즈": 1,
	"서커스": 1,
	"의": 3,
	"최신": 1,
	"앱": 7,
	"통해": 1,
	"전": 2,
	"세계": 2,
	"부모님": 1,
	"그": 3,
	"아이": 1,
	"세": 4,
	"모든": 1,
	"숲": 3,
	"관": 2,
	"것": 1,
	"음악": 2,
	"내레이션": 2,
	"작품": 2,
	"일상": 2,
	"취침": 3,
	"안성맞춤": 2,
	"어린이": 6,
	"마리": 2,
	"서로": 1,
	"다른": 1,
	"꿈": 1,
	"체험": 1,
	"불": 1,
	"잠자리": 1,
	"각각": 1,
	"여러": 1,
	"가지": 1,
	"익살": 1,
	"동작": 2,
	"주무": 1,
	"주민": 1,
	"여러분": 1,
	"수상": 1,
	"아티스트": 1,
	"삽화": 1,
	"텍스처": 1,
	"모델링": 1,
	"조명": 1,
	"결": 1,
	"경탄": 2,
	"장면": 1,
	"온갖": 1,
	"정열": 1,
	"노력": 1,
	"특징": 1,
	"디자인": 2,
	"애니메이션": 1,
	"대화": 1,
	"사슴": 1,
	"스컹크": 1,
	"딱따구리": 1,
	"얼룩": 1,
	"다람쥐": 1,
	"두더지": 1,
	"여우": 1,
	"곰": 1,
	"오토": 1,
	"플레이": 1,
	"모드": 1,
	"시종일관": 1,
	"깜짝": 1,
	"쇼": 1,
	"맞춤": 1,
	"음향": 1,
	"세션": 1,
	"길이": 1,
	"개": 1,
	"언어": 1,
	"영어": 1,
	"독일어": 1,
	"스페인어": 1,
	"프랑스어": 1,
	"네덜란드어": 1,
	"스웨덴어": 1,
	"이태리어": 1,
	"노르웨이어": 1,
	"브라질": 1,
	"포르투갈어": 1,
	"러시아어": 1,
	"터키어": 1,
	"한국어": 1,
	"중국어": 1,
	"일본어": 1,
	"용": 1,
	"베를린": 1,
	"소재": 1,
	"스튜디오": 1,
	"위": 2,
	"고급": 1,
	"게임": 1,
	"개발": 2,
	"자신": 1,
	"부모": 1,
	"열정": 1,
	"심혈": 1,
	"다해": 1,
	"제작": 1,
	"임": 1,
	"위해": 1,
	"최고": 2,
	"일러스트레이터": 1,
	"선택": 1,
	"함": 1,
	"제공": 2,
	"당신": 1,
	"자녀": 1,
	"풍요": 1,
	"삶": 1
}