{
	"어린이": 1,
	"유아": 2,
	"위": 5,
	"공룡": 4,
	"무료": 2,
	"색칠": 2,
	"공부": 1,
	"아이": 3,
	"이": 3,
	"착색": 2,
	"동물": 3,
	"게임": 3,
	"무엇": 1,
	"관": 1,
	"것입": 1,
	"응용": 2,
	"프로그램": 2,
	"개": 1,
	"이미지": 1,
	"포함": 1,
	"전체": 1,
	"지역": 1,
	"수": 4,
	"연필": 1,
	"브러시": 1,
	"그릴": 1,
	"지우개": 1,
	"사용": 1,
	"사진": 1,
	"장치": 1,
	"갤러리": 1,
	"저장": 1,
	"소녀": 2,
	"소년": 2,
	"모두": 1,
	"사랑": 1,
	"색": 3,
	"색상": 1,
	"디노": 3,
	"것": 2,
	"아기": 3,
	"학교": 1,
	"학생": 1,
	"창의력": 1,
	"자극": 1,
	"십대": 1,
	"나": 1,
	"성인": 1,
	"일": 1,
	"당신": 2,
	"를": 1,
	"거나": 1,
	"경우": 1,
	"책": 1,
	"티라노": 1,
	"우루스": 1,
	"렉스": 2,
	"초식": 2,
	"엄마": 1,
	"화석": 1,
	"계란": 1,
	"페이지": 1,
	"모든": 1,
	"팬": 1,
	"신청서": 1,
	"매력": 1,
	"로": 1,
	"왕성": 1,
	"디자인": 1,
	"의": 1,
	"항상": 1,
	"설계": 1,
	"통해": 1,
	"자녀": 1,
	"최상": 1,
	"서비스": 1,
	"제공": 1,
	"노력": 1,
	"각": 1,
	"연령": 1,
	"대별": 1,
	"별도": 1,
	"진화": 1,
	"단계": 1,
	"귀하": 1,
	"아들": 1,
	"전달": 2,
	"기능": 1,
	"대한": 1,
	"우리": 1,
	"믿음": 1,
	"플레이": 1,
	"자신": 1,
	"동료": 1,
	"및": 1,
	"주변": 1,
	"환경": 1,
	"의사": 1,
	"소통": 1,
	"사고": 1,
	"방식": 1
}