{
	"이": 3,
	"무료": 1,
	"퍼즐": 8,
	"게임": 6,
	"말": 1,
	"양": 1,
	"오리": 1,
	"닭": 1,
	"코끼리": 1,
	"개": 3,
	"고양이": 1,
	"토끼": 1,
	"나비": 1,
	"원숭이": 1,
	"물고기": 1,
	"등": 2,
	"가지": 3,
	"동물": 5,
	"연주": 1,
	"아이": 1,
	"일치": 1,
	"촉각": 1,
	"및": 5,
	"정밀": 1,
	"운동": 1,
	"기술": 1,
	"개발": 1,
	"수": 2,
	"자폐": 1,
	"를": 1,
	"포함": 1,
	"미취": 1,
	"학": 1,
	"아동": 2,
	"아기": 1,
	"위": 2,
	"재미": 2,
	"교육": 1,
	"학습": 2,
	"수중": 1,
	"농장": 1,
	"정글": 1,
	"동물원": 1,
	"애완": 1,
	"용": 1,
	"이름": 1,
	"목소리": 1,
	"항상": 1,
	"자녀": 2,
	"격려": 1,
	"칭찬": 1,
	"어휘": 1,
	"기억": 2,
	"인지": 1,
	"능력": 1,
	"지속": 1,
	"구축": 1,
	"동기": 1,
	"부여": 1,
	"반복": 1,
	"재생": 1,
	"위해": 1,
	"애니메이션": 2,
	"발음": 2,
	"소리": 2,
	"상호": 2,
	"작용": 2,
	"몇": 1,
	"시간": 1,
	"동안": 1,
	"것": 1,
	"이제": 1,
	"테마": 3,
	"추가": 1,
	"장면": 1,
	"객체": 1,
	"직소": 1,
	"풍모": 1,
	"직관": 1,
	"인": 2,
	"친": 1,
	"적": 1,
	"인터페이스": 1,
	"언어": 1,
	"이상": 1,
	"조각": 2,
	"장치": 1,
	"화면": 1,
	"만화": 1,
	"일러스트": 1,
	"배경": 1,
	"음악": 1,
	"각": 1,
	"해결": 1,
	"후": 1,
	"풍선": 1,
	"응원": 1,
	"음식": 1,
	"주방": 1,
	"가구": 1,
	"공룡": 1,
	"자동차": 1,
	"더": 1,
	"다른": 1,
	"앱": 2,
	"확인": 1,
	"피드백": 1,
	"디자인": 1,
	"개선": 1,
	"방법": 1,
	"대한": 1,
	"의견": 1,
	"제안": 1,
	"웹": 1,
	"사이트": 1,
	"방문": 1,
	"메시지": 1
}