{
	"전": 2,
	"피자": 19,
	"만들기": 9,
	"시도": 1,
	"최고": 2,
	"요리": 5,
	"주방": 3,
	"오신": 1,
	"것": 1,
	"환영": 1,
	"시작": 3,
	"스낵": 3,
	"조리": 3,
	"조리법": 2,
	"은": 1,
	"음식": 3,
	"애호가": 1,
	"위": 1,
	"장소": 1,
	"가장": 1,
	"쿡": 1,
	"그냥": 1,
	"마스터": 1,
	"쇼핑": 3,
	"먼저": 1,
	"간식": 2,
	"모든": 2,
	"재료": 3,
	"반죽": 5,
	"이": 1,
	"사용": 1,
	"만듭니": 1,
	"모양": 2,
	"절단": 3,
	"다른": 1,
	"야채": 4,
	"토핑을위": 1,
	"방식": 1,
	"굽": 1,
	"기와": 1,
	"토핑": 3,
	"이제": 2,
	"당신": 1,
	"구울": 1,
	"준비": 3,
	"오븐": 1,
	"다음": 1,
	"채소": 1,
	"풍모": 1,
	"능력": 1,
	"향상": 1,
	"체험": 1,
	"및": 1,
	"장면": 1,
	"환상": 1,
	"애니메이션": 1,
	"인터랙티브": 1,
	"환경": 1,
	"메이커": 1,
	"게임": 1,
	"위해": 1,
	"데": 1,
	"추가": 1,
	"중독": 1,
	"음향": 1,
	"효과": 1,
	"매력": 1,
	"인터": 1,
	"랙티브": 1,
	"그래픽": 1
}