{
	"포브스": 1,
	"번창": 1,
	"잡지": 1,
	"자폐증": 2,
	"육아": 1,
	"브리즈번": 1,
	"키즈": 1,
	"스": 3,
	"피치": 3,
	"칙": 1,
	"테라": 1,
	"피": 1,
	"연설": 2,
	"생활": 1,
	"교사": 1,
	"사회": 1,
	"영향": 1,
	"상": 1,
	"수상": 1,
	"및": 5,
	"시작": 3,
	"프로그램": 2,
	"지원": 1,
	"자극": 1,
	"인": 2,
	"교육": 2,
	"환경": 2,
	"자녀": 3,
	"소리": 4,
	"말": 2,
	"연습": 2,
	"수": 4,
	"고안": 1,
	"음성": 1,
	"치료": 2,
	"응용": 1,
	"우리": 2,
	"개": 2,
	"이상": 2,
	"관행": 2,
	"유아": 1,
	"발화": 1,
	"지연": 1,
	"언어": 1,
	"실력": 1,
	"저하": 1,
	"다운": 1,
	"증후군": 1,
	"감각": 1,
	"장애": 1,
	"어린이": 1,
	"단어": 2,
	"생": 1,
	"유발": 1,
	"위해": 3,
	"번": 1,
	"사용": 6,
	"왜": 1,
	"블": 1,
	"러스": 1,
	"효과": 4,
	"개발": 1,
	"과학": 3,
	"입증": 3,
	"비디오": 6,
	"모델링": 2,
	"운동": 1,
	"액": 1,
	"티비": 1,
	"티": 1,
	"모자": 3,
	"미니": 2,
	"게임": 2,
	"등": 2,
	"새": 2,
	"콘텐츠": 5,
	"출시": 1,
	"섹션": 1,
	"조기": 1,
	"내": 2,
	"때": 2,
	"모양": 1,
	"색상": 1,
	"시간": 2,
	"이건": 1,
	"몸": 1,
	"입": 1,
	"체육관": 1,
	"동물": 1,
	"왕국": 1,
	"바퀴": 1,
	"달리": 1,
	"노래": 1,
	"추측": 2,
	"더": 1,
	"얼굴": 1,
	"탐지": 1,
	"마스크": 1,
	"특수": 1,
	"실시간": 1,
	"경험": 1,
	"진행": 1,
	"함": 1,
	"스티커": 2,
	"북": 1,
	"대화": 1,
	"설계": 1,
	"재미": 1,
	"해제": 2,
	"활동": 1,
	"무료": 3,
	"시도": 1,
	"학습": 2,
	"기술": 1,
	"몰입": 1,
	"형": 1,
	"조성하": 1,
	"아이": 2,
	"통해": 3,
	"동료": 2,
	"관찰": 2,
	"자신": 1,
	"역": 1,
	"적": 1,
	"신경": 1,
	"발사": 1,
	"것": 2,
	"이": 1,
	"출판": 1,
	"캘리포니아": 1,
	"대학": 1,
	"로스": 1,
	"앤젤레스": 1,
	"연구": 1,
	"확인": 2,
	"바": 1,
	"발달": 1,
	"매우": 1,
	"정기": 1,
	"공개": 1,
	"가지": 1,
	"포함": 1,
	"거의": 1,
	"무한대": 1,
	"제공": 1,
	"컨텐츠": 1,
	"추가": 1,
	"항상": 1,
	"노력": 1,
	"구독": 4,
	"가격": 1,
	"조건": 1,
	"일": 1,
	"평가판": 2,
	"액세스": 3,
	"앱": 1,
	"테스트": 1,
	"모든": 1,
	"계속": 1,
	"계정": 3,
	"월": 2,
	"달러": 1,
	"구독료": 1,
	"부과": 1,
	"반복": 1,
	"거래": 1,
	"현재": 1,
	"최소": 1,
	"전": 1,
	"해지": 1,
	"자동": 2,
	"갱신": 2,
	"정보": 2,
	"관리": 1,
	"거나": 2,
	"언제": 1,
	"취소": 1,
	"중지": 1,
	"기간": 1,
	"중": 1,
	"부분": 1,
	"귀하": 1,
	"가입": 1,
	"자격": 1,
	"상실": 1,
	"전체": 1,
	"이용": 1,
	"약관": 1,
	"개인": 1,
	"보호": 1,
	"정책": 1
}