{
	"농장": 3,
	"노래": 4,
	"및": 1,
	"아동": 1,
	"비디오": 4,
	"환영": 2,
	"당신": 17,
	"그것": 2,
	"재미": 2,
	"수천": 2,
	"시간": 4,
	"수": 8,
	"어린이": 1,
	"우리": 10,
	"응용": 5,
	"프로그램": 5,
	"오신": 1,
	"것": 4,
	"알": 1,
	"지금": 3,
	"번의": 1,
	"클릭": 1,
	"모바일": 3,
	"화면": 1,
	"결정": 1,
	"왜": 1,
	"다운로드": 3,
	"인터넷": 2,
	"가장": 1,
	"동영상": 1,
	"중": 1,
	"하나": 1,
	"집": 1,
	"차": 1,
	"어디": 2,
	"서나": 2,
	"쇼핑": 1,
	"때": 2,
	"항상": 4,
	"콘텐츠": 1,
	"이": 1,
	"볼": 1,
	"연결": 1,
	"작동": 1,
	"때문": 1,
	"단지": 1,
	"번만": 1,
	"를": 1,
	"휴대": 1,
	"기기": 1,
	"또한": 3,
	"태블릿": 1,
	"최적화": 1,
	"운영": 1,
	"체제": 1,
	"모든": 1,
	"아이": 1,
	"춤": 2,
	"웃음": 1,
	"옆": 1,
	"문자": 1,
	"사방": 1,
	"공유": 1,
	"제공": 1,
	"모두": 1,
	"도움": 1,
	"실천": 1,
	"대한": 1,
	"지식": 1,
	"수학": 1,
	"문제": 1,
	"덧셈": 1,
	"뺄셈": 1,
	"곱셈": 1,
	"가지": 1,
	"독서": 1,
	"더": 1,
	"학습": 1,
	"다음": 1,
	"즐거움": 3,
	"박수": 1,
	"개구리": 1,
	"파티": 1,
	"내": 2,
	"친구": 2,
	"돌고래": 1,
	"나": 1,
	"컵": 1,
	"기린": 1,
	"우유": 1,
	"쌀": 1,
	"늑대": 1,
	"버스": 1,
	"바퀴": 1,
	"현재": 1,
	"민족": 1,
	"데리": 1,
	"최고": 1,
	"경험": 1,
	"소리": 1,
	"색채": 1,
	"가득": 2,
	"행복": 1
}