{
	"소녀": 3,
	"소년": 3,
	"위": 8,
	"애완": 5,
	"동물": 5,
	"관리": 2,
	"게임": 9,
	"아이": 5,
	"조랑말": 17,
	"레인보우": 3,
	"브리트니": 3,
	"몰리": 3,
	"로지": 3,
	"아기": 15,
	"목마": 1,
	"시간": 1,
	"여행": 1,
	"목욕": 3,
	"사료": 1,
	"노래": 1,
	"기저귀": 3,
	"옷": 1,
	"등": 1,
	"가상": 4,
	"당신": 3,
	"방식": 3,
	"방": 4,
	"장식": 2,
	"이": 4,
	"말": 2,
	"안고": 1,
	"유니콘": 3,
	"언니": 1,
	"돌": 1,
	"냄새": 2,
	"나": 2,
	"및": 6,
	"변기": 2,
	"변경": 1,
	"훈련": 2,
	"수": 4,
	"수식": 1,
	"브로콜리": 1,
	"준비": 1,
	"먹이": 2,
	"자매": 4,
	"거품": 1,
	"패션": 1,
	"옷차림": 1,
	"것": 2,
	"귀하": 1,
	"가장": 5,
	"의상": 1,
	"스타일": 1,
	"무지개": 4,
	"모든": 2,
	"색상": 1,
	"베이비": 1,
	"드레스": 1,
	"여성": 1,
	"스커트": 1,
	"활": 1,
	"액세서리": 2,
	"중": 1,
	"선택": 2,
	"벽지": 1,
	"디자인": 1,
	"패턴": 1,
	"추가": 1,
	"가구": 1,
	"객실": 1,
	"판타지": 1,
	"보이": 1,
	"그것": 1,
	"어린이": 3,
	"마찬가지": 1,
	"선물": 2,
	"사랑": 1,
	"톤": 1,
	"풀": 1,
	"놀람": 2,
	"장난감": 2,
	"모두": 1,
	"고양이": 1,
	"공룡": 1,
	"플러시": 1,
	"여동생": 1,
	"마리": 1,
	"누이": 1,
	"잠": 1,
	"청": 1,
	"복장": 1,
	"차려": 1,
	"견": 1,
	"벨벳": 1,
	"비디오": 1,
	"보고": 1,
	"더": 3,
	"대해": 2,
	"소개": 1,
	"유아": 1,
	"제작": 1,
	"테스트": 1,
	"창의력": 1,
	"그": 1,
	"재미": 1,
	"교육": 1,
	"전": 1,
	"세계": 1,
	"수백만": 1,
	"명의": 1,
	"의미": 1,
	"모바일": 1,
	"경험": 1,
	"제공": 1,
	"위해": 1,
	"노력": 1,
	"학부모": 1,
	"메시지": 1,
	"앱": 2,
	"무료": 1,
	"다운로드": 2,
	"사용": 1,
	"실제": 1,
	"돈": 1,
	"구입": 1,
	"내": 1,
	"아이템": 1,
	"개인": 1,
	"정보": 1,
	"보호": 1,
	"정책": 1,
	"이용": 1,
	"약관": 1,
	"동의": 1,
	"투투": 1,
	"툰": 1,
	"즐거움": 1,
	"발견": 1,
	"채널": 1,
	"구독": 1,
	"우리": 1,
	"블로그": 1
}