{
	"이": 4,
	"빵집": 3,
	"얼음": 4,
	"공주": 28,
	"오신": 1,
	"것": 5,
	"환영": 1,
	"여기": 1,
	"케이크": 35,
	"세": 1,
	"이하": 1,
	"소녀": 7,
	"위": 10,
	"베이": 9,
	"킹": 9,
	"게임": 20,
	"법": 2,
	"수": 5,
	"나": 2,
	"근처": 2,
	"제과점": 3,
	"이제": 1,
	"인형": 4,
	"무성": 1,
	"무지개": 3,
	"크림": 4,
	"퐁당": 3,
	"차려": 2,
	"당신": 9,
	"또한": 1,
	"마술": 6,
	"지팡이": 3,
	"선택": 1,
	"사실": 1,
	"여자": 1,
	"살롱": 3,
	"왕실": 1,
	"팝": 1,
	"어쩌면": 1,
	"우리": 8,
	"아이": 1,
	"케익": 2,
	"베이커리": 3,
	"굽": 3,
	"방법": 1,
	"배우자": 1,
	"특징": 1,
	"성의": 1,
	"갤러리아": 1,
	"게": 3,
	"타우": 2,
	"만듭니": 1,
	"그것": 1,
	"신부": 1,
	"신랑": 1,
	"결혼식": 1,
	"파티": 1,
	"왕자": 2,
	"웨딩": 1,
	"일반": 1,
	"사랑": 1,
	"설탕": 2,
	"만": 1,
	"준비": 3,
	"여러분": 1,
	"퀸": 1,
	"최고": 2,
	"빵": 2,
	"사람": 1,
	"내": 1,
	"먼저": 1,
	"위해": 2,
	"오븐": 1,
	"반죽": 1,
	"정말": 2,
	"타임": 1,
	"제": 1,
	"제국": 1,
	"시간": 2,
	"부엌": 1,
	"요리": 3,
	"구멍": 1,
	"마법": 4,
	"구성": 1,
	"때": 1,
	"너": 3,
	"컵": 1,
	"왕관": 1,
	"머리카락": 1,
	"패션": 4,
	"헤어": 1,
	"스타일": 1,
	"그": 2,
	"눈썹": 1,
	"연필": 1,
	"립스틱": 1,
	"트렌디": 1,
	"메이크업": 2,
	"디자인": 2,
	"드레스": 4,
	"여부": 1,
	"기술": 3,
	"상상력": 1,
	"로얄": 1,
	"의상": 1,
	"액세서리": 1,
	"지금": 1,
	"음식": 1,
	"재미": 1,
	"여자애": 1,
	"눈": 2,
	"반짝": 1,
	"식용": 1,
	"착빙": 2,
	"꽃": 1,
	"장식": 1,
	"루아": 1,
	"복장": 1,
	"스타": 1,
	"다이아몬드": 1,
	"레이스": 1,
	"가장자리": 1,
	"아름": 1,
	"데": 1,
	"제일": 1,
	"요리사": 1,
	"업": 1,
	"스킬": 1,
	"얘": 1,
	"오늘": 1,
	"다운로드": 1,
	"소개": 1,
	"은": 1,
	"모바일": 1,
	"플랫폼": 1,
	"캐": 1,
	"주얼": 1,
	"전문": 1,
	"온": 1,
	"가족": 1,
	"혁신": 1,
	"교육": 1,
	"제공": 1,
	"통해": 1,
	"기본": 1,
	"생활": 1,
	"습관": 1,
	"방문": 1,
	"도움말": 1,
	"문의": 2,
	"생각": 1,
	"저희": 1,
	"질문": 1,
	"제안": 1,
	"지원": 1
}