{
	"수": 8,
	"개": 3,
	"휴식": 2,
	"편안": 2,
	"사운드": 7,
	"분위기": 2,
	"이상": 1,
	"필요": 2,
	"완벽": 1,
	"믹스": 2,
	"훌륭": 1,
	"콜렉션": 1,
	"선사": 1,
	"다양한": 1,
	"종류": 2,
	"빗소리": 2,
	"자연": 2,
	"소리": 6,
	"도시": 2,
	"백색": 3,
	"소음": 1,
	"악기": 1,
	"중": 1,
	"대": 1,
	"선택": 2,
	"즐겨찾": 1,
	"저장": 1,
	"두": 1,
	"계": 1,
	"타이머": 1,
	"시간": 1,
	"설정": 1,
	"앱": 5,
	"자동": 1,
	"인터넷": 1,
	"접속": 1,
	"데이터": 1,
	"용량": 1,
	"걱정": 1,
	"언제": 1,
	"사용": 2,
	"4": 1,
	"그룹": 1,
	"32개": 1,
	"엄선": 1,
	"빗": 1,
	"창": 1,
	"파도": 1,
	"천둥": 1,
	"숲": 1,
	"개울": 1,
	"폭포": 1,
	"지하철": 1,
	"철도": 1,
	"선풍기": 1,
	"비행기": 1,
	"명상": 2,
	"잡음": 2,
	"피아노": 1,
	"오리엔탈": 1,
	"플룻": 1,
	"앱은": 1,
	"일": 1,
	"집중력": 1,
	"세": 1,
	"가지": 1,
	"인기": 1,
	"포함": 1,
	"화이트": 1,
	"노이즈": 3,
	"핑크": 1,
	"브라운": 1,
	"방안": 1,
	"추가하길": 1,
	"특정": 1,
	"relaxio+sleepo@gmail.": 1,
	"으": 1,
	"행복": 1,
	"수면": 1
}