{
	"5,000": 2,
	"8mb": 1,
	"481mb": 1,
	"•": 40,
	"5000+": 1,
	"460": 2,
	"670": 2,
	"&": 1,
	"1-100": 1,
	"서명": 2,
	"단어": 5,
	"사전": 2,
	"스페셜": 1,
	"에디션": 1,
	"응용": 6,
	"프로그램": 6,
	"다있다": 1,
	"해결": 2,
	"보장": 2,
	"당신": 4,
	"문제": 2,
	"발생": 2,
	"경우": 3,
	"이메일": 2,
	"바": 2,
	"판매": 1,
	"기간": 1,
	"한정": 1,
	"상품": 1,
	"완벽": 1,
	"대화": 1,
	"형": 1,
	"앱": 1,
	"퀴즈": 3,
	"기능": 2,
	"조정": 2,
	"가능": 1,
	"슬로우": 2,
	"모션": 2,
	"재생": 4,
	"베스트": 1,
	"휴대폰": 1,
	"정제를위한": 1,
	"보편적": 1,
	"인터넷": 1,
	"옵션": 1,
	"필요": 1,
	"설정": 1,
	"버튼": 1,
	"아래에있는": 1,
	"동영상": 2,
	"다운로드": 1,
	"내부": 2,
	"저장": 1,
	"와이파": 1,
	"공간": 1,
	"스토리": 1,
	"4백81메가바이트": 1,
	"8MB": 1,
	"사용": 1,
	"언어": 1,
	"비디오": 4,
	"변환": 1,
	"5000": 1,
	"부호": 1,
	"가지": 1,
	"방법": 1,
	"의미": 1,
	"시간": 1,
	"돈": 1,
	"날짜": 1,
	"일반": 1,
	"번호": 2,
	"서수": 1,
	"알파벳": 1,
	"인식": 1,
	"전체": 1,
	"연습": 1,
	"재미": 1,
	"특징": 1,
	"종류": 1,
	"목록": 1,
	"만들기": 1,
	"1": 1,
	"100": 1,
	"모든": 1,
	"다음": 1,
	"이전": 1,
	"출근": 1,
	"화면": 1,
	"루프": 1,
	"검색": 1,
	"카테고리": 1,
	"특허": 1,
	"기술": 1,
	"청각": 1,
	"사람": 1,
	"때": 1,
	"일반적": 1,
	"목소리를하지": 1,
	"것": 1,
	"오디오": 1,
	"귀하": 1,
	"지원": 1,
	"감사": 1
}{
	"5,000": 2,
	"8mb": 1,
	"481mb": 1,
	"•": 40,
	"5000+": 1,
	"460": 2,
	"670": 2,
	"&": 1,
	"1-100": 1,
	"서명": 2,
	"단어": 5,
	"사전": 2,
	"스페셜": 1,
	"에디션": 1,
	"응용": 6,
	"프로그램": 6,
	"다있다": 1,
	"해결": 2,
	"보장": 2,
	"당신": 4,
	"문제": 2,
	"발생": 2,
	"경우": 3,
	"이메일": 2,
	"바": 2,
	"판매": 1,
	"기간": 1,
	"한정": 1,
	"상품": 1,
	"완벽": 1,
	"대화": 1,
	"형": 1,
	"앱": 1,
	"퀴즈": 3,
	"기능": 2,
	"조정": 2,
	"가능": 1,
	"슬로우": 2,
	"모션": 2,
	"재생": 4,
	"베스트": 1,
	"휴대폰": 1,
	"정제를위한": 1,
	"보편적": 1,
	"인터넷": 1,
	"옵션": 1,
	"필요": 1,
	"설정": 1,
	"버튼": 1,
	"아래에있는": 1,
	"동영상": 2,
	"다운로드": 1,
	"내부": 2,
	"저장": 1,
	"와이파": 1,
	"공간": 1,
	"스토리": 1,
	"4백81메가바이트": 1,
	"8MB": 1,
	"사용": 1,
	"언어": 1,
	"비디오": 4,
	"변환": 1,
	"5000": 1,
	"부호": 1,
	"가지": 1,
	"방법": 1,
	"의미": 1,
	"시간": 1,
	"돈": 1,
	"날짜": 1,
	"일반": 1,
	"번호": 2,
	"서수": 1,
	"알파벳": 1,
	"인식": 1,
	"전체": 1,
	"연습": 1,
	"재미": 1,
	"특징": 1,
	"종류": 1,
	"목록": 1,
	"만들기": 1,
	"1": 1,
	"100": 1,
	"모든": 1,
	"다음": 1,
	"이전": 1,
	"출근": 1,
	"화면": 1,
	"루프": 1,
	"검색": 1,
	"카테고리": 1,
	"특허": 1,
	"기술": 1,
	"청각": 1,
	"사람": 1,
	"때": 1,
	"일반적": 1,
	"목소리를하지": 1,
	"것": 1,
	"오디오": 1,
	"귀하": 1,
	"지원": 1,
	"감사": 1
}