{
	"—": 2,
	"2-11": 2,
	"1.": 2,
	"2.": 2,
	"$9": 1,
	"99": 1,
	"80": 2,
	"7": 2,
	"“read": 2,
	"myself”": 1,
	"me”": 1,
	"•": 15,
	"어린이들": 1,
	"영감": 1,
	"세계": 3,
	"발견": 2,
	"강력": 1,
	"문맹": 1,
	"퇴치": 1,
	"기술": 1,
	"개발": 1,
	"수": 7,
	"디지털": 1,
	"도서관": 1,
	"앱": 4,
	"사용": 2,
	"아이들": 1,
	"광고": 1,
	"애니메이션": 1,
	"비디오": 1,
	"게임이": 1,
	"환경": 1,
	"독": 4,
	"학습": 3,
	"해설": 1,
	"서적": 4,
	"책": 2,
	"액세스": 2,
	"향상": 1,
	"대화식": 1,
	"자료": 2,
	"활동": 1,
	"퀴즈": 1,
	"자녀들": 1,
	"자신": 1,
	"독창적": 1,
	"비소설": 1,
	"관련": 2,
	"자녀": 6,
	"성장": 1,
	"나": 3,
	"학년": 2,
	"콘텐츠": 4,
	"영역별": 1,
	"분류": 1,
	"확장": 1,
	"카탈로그": 1,
	"응용": 1,
	"프로그램": 1,
	"세": 1,
	"사이": 1,
	"부모": 1,
	"다음": 2,
	"사람들": 2,
	"수준": 1,
	"정기": 1,
	"월간": 1,
	"구독료": 1,
	"9.99": 1,
	"설치": 1,
	"때": 1,
	"최대": 1,
	"할인": 1,
	"일": 1,
	"동안": 1,
	"무료": 1,
	"언제": 1,
	"취소": 1,
	"형식": 1,
	"추": 1,
	"주요": 1,
	"기능": 1,
	"단어": 7,
	"인식을위한": 1,
	"하이라이트": 1,
	"나레이션": 1,
	"발음": 1,
	"보조": 1,
	"문맥": 1,
	"사전": 1,
	"내장": 1,
	"오프라": 1,
	"어린이를위한": 3,
	"논픽션": 1,
	"컬렉션": 1,
	"중": 1,
	"하나": 1,
	"글로벌": 1,
	"특별": 1,
	"지원": 1,
	"범주": 1,
	"적용": 1,
	"범위": 1,
	"알파벳": 1,
	"땅": 1,
	"동물": 1,
	"달력": 1,
	"인물": 1,
	"교육": 1,
	"색상": 1,
	"대화체": 1,
	"개": 4,
	"유형": 1,
	"생태계": 1,
	"지구": 1,
	"유명한": 2,
	"탐험가": 1,
	"우정": 1,
	"건강": 1,
	"복지": 1,
	"역사": 1,
	"휴일": 1,
	"축제": 1,
	"원주민": 1,
	"라이프": 1,
	"사이클": 1,
	"수학": 2,
	"파닉스,": 1,
	"아동": 1,
	"물리학": 1,
	"시": 1,
	"직업": 1,
	"운율": 1,
	"수수께끼": 1,
	"과학": 1,
	"감각": 1,
	"스페인어": 1,
	"시력": 1,
	"노래": 4,
	"우주": 1,
	"천문학": 1,
	"이야기": 1,
	"시간": 1,
	"여행": 1,
	"미국": 2,
	"미국,": 1,
	"어휘": 1,
	"표창": 1,
	"명소": 1,
	"부르기": 1,
	"우리": 4,
	"첫": 2,
	"번": 1,
	"화면": 2,
	"보호": 4,
	"게이트": 1,
	"추가": 1,
	"온라인": 1,
	"정보": 3,
	"심각": 2,
	"것": 1,
	"성인": 1,
	"구매": 1,
	"이용": 2,
	"약관": 2,
	"정책": 2,
	"아래": 1,
	"링크": 1,
	"나열": 1
}{
	"—": 2,
	"2-11": 2,
	"1.": 2,
	"2.": 2,
	"$9": 1,
	"99": 1,
	"80": 2,
	"7": 2,
	"“read": 2,
	"myself”": 1,
	"me”": 1,
	"•": 15,
	"어린이들": 1,
	"영감": 1,
	"세계": 3,
	"발견": 2,
	"강력": 1,
	"문맹": 1,
	"퇴치": 1,
	"기술": 1,
	"개발": 1,
	"수": 7,
	"디지털": 1,
	"도서관": 1,
	"앱": 4,
	"사용": 2,
	"아이들": 1,
	"광고": 1,
	"애니메이션": 1,
	"비디오": 1,
	"게임이": 1,
	"환경": 1,
	"독": 4,
	"학습": 3,
	"해설": 1,
	"서적": 4,
	"책": 2,
	"액세스": 2,
	"향상": 1,
	"대화식": 1,
	"자료": 2,
	"활동": 1,
	"퀴즈": 1,
	"자녀들": 1,
	"자신": 1,
	"독창적": 1,
	"비소설": 1,
	"관련": 2,
	"자녀": 6,
	"성장": 1,
	"나": 3,
	"학년": 2,
	"콘텐츠": 4,
	"영역별": 1,
	"분류": 1,
	"확장": 1,
	"카탈로그": 1,
	"응용": 1,
	"프로그램": 1,
	"세": 1,
	"사이": 1,
	"부모": 1,
	"다음": 2,
	"사람들": 2,
	"수준": 1,
	"정기": 1,
	"월간": 1,
	"구독료": 1,
	"9.99": 1,
	"설치": 1,
	"때": 1,
	"최대": 1,
	"할인": 1,
	"일": 1,
	"동안": 1,
	"무료": 1,
	"언제": 1,
	"취소": 1,
	"형식": 1,
	"추": 1,
	"주요": 1,
	"기능": 1,
	"단어": 7,
	"인식을위한": 1,
	"하이라이트": 1,
	"나레이션": 1,
	"발음": 1,
	"보조": 1,
	"문맥": 1,
	"사전": 1,
	"내장": 1,
	"오프라": 1,
	"어린이를위한": 3,
	"논픽션": 1,
	"컬렉션": 1,
	"중": 1,
	"하나": 1,
	"글로벌": 1,
	"특별": 1,
	"지원": 1,
	"범주": 1,
	"적용": 1,
	"범위": 1,
	"알파벳": 1,
	"땅": 1,
	"동물": 1,
	"달력": 1,
	"인물": 1,
	"교육": 1,
	"색상": 1,
	"대화체": 1,
	"개": 4,
	"유형": 1,
	"생태계": 1,
	"지구": 1,
	"유명한": 2,
	"탐험가": 1,
	"우정": 1,
	"건강": 1,
	"복지": 1,
	"역사": 1,
	"휴일": 1,
	"축제": 1,
	"원주민": 1,
	"라이프": 1,
	"사이클": 1,
	"수학": 2,
	"파닉스,": 1,
	"아동": 1,
	"물리학": 1,
	"시": 1,
	"직업": 1,
	"운율": 1,
	"수수께끼": 1,
	"과학": 1,
	"감각": 1,
	"스페인어": 1,
	"시력": 1,
	"노래": 4,
	"우주": 1,
	"천문학": 1,
	"이야기": 1,
	"시간": 1,
	"여행": 1,
	"미국": 2,
	"미국,": 1,
	"어휘": 1,
	"표창": 1,
	"명소": 1,
	"부르기": 1,
	"우리": 4,
	"첫": 2,
	"번": 1,
	"화면": 2,
	"보호": 4,
	"게이트": 1,
	"추가": 1,
	"온라인": 1,
	"정보": 3,
	"심각": 2,
	"것": 1,
	"성인": 1,
	"구매": 1,
	"이용": 2,
	"약관": 2,
	"정책": 2,
	"아래": 1,
	"링크": 1,
	"나열": 1
}