{
	"3": 2,
	"7": 4,
	"&": 1,
	"155": 2,
	"6": 2,
	"✔": 12,
	"26": 2,
	"20": 4,
	"1": 2,
	"34": 2,
	"32": 2,
	"24": 2,
	"19": 2,
	"유치원": 2,
	"퍼즐": 7,
	"미취학": 2,
	"어린이": 2,
	"투": 1,
	"세": 1,
	"의": 1,
	"능력": 4,
	"개발": 3,
	"수": 2,
	"고안": 1,
	"교육": 2,
	"재미": 3,
	"게임": 7,
	"같은": 1,
	"무료": 1,
	"지그": 1,
	"소": 1,
	"재생": 2,
	"동안": 2,
	"아이": 2,
	"매칭": 1,
	"촉각": 1,
	"운동": 1,
	"데": 1,
	"도움이": 1,
	"그것": 2,
	"자폐증": 1,
	"특별한": 1,
	"요구": 1,
	"포함": 2,
	"취학": 1,
	"전": 1,
	"유아를위한": 1,
	"학습": 2,
	"영어": 1,
	"독일어": 1,
	"스페인어": 1,
	"러시아어": 1,
	"포르투갈어": 1,
	"프랑스어": 1,
	"폴란드": 1,
	"이": 1,
	"개": 7,
	"언어": 1,
	"지원": 1,
	"다음": 1,
	"범주": 1,
	"개체": 1,
	"라틴어": 1,
	"문자": 1,
	"자신": 3,
	"발음": 2,
	"숫자": 1,
	"이름": 4,
	"동물": 3,
	"조류": 1,
	"그": 3,
	"소리": 1,
	"과일": 1,
	"야채": 1,
	"컬러": 1,
	"한": 1,
	"차량": 1,
	"장난감": 1,
	"인형": 1,
	"당신": 4,
	"아이들": 1,
	"애완": 1,
	"농장": 1,
	"정글": 1,
	"동물원": 1,
	"것": 2,
	"목소리": 1,
	"격려": 1,
	"자녀": 2,
	"칭찬": 1,
	"어휘": 1,
	"메모리": 1,
	"구축": 1,
	"동기": 1,
	"부": 1,
	"인지": 1,
	"반복": 1,
	"장려": 1,
	"애니메이션": 1,
	"음향": 1,
	"효과": 1,
	"작용": 1,
	"풍부": 1,
	"유": 1,
	"일반": 1,
	"발생": 1,
	"조각": 1,
	"걱정": 1,
	"않아도됩니": 1,
	"스마트": 1,
	"기술": 2,
	"우리": 2,
	"목표": 1,
	"동료": 1,
	"주변": 1,
	"환경": 1,
	"소통": 1,
	"법": 1,
	"중요": 1,
	"삶": 1,
	"습득": 1,
	"그들": 1,
	"시각적": 1,
	"아이들을위한": 1,
	"최고": 1,
	"가치": 1,
	"제공": 1,
	"특정": 1,
	"연령": 1,
	"그룹": 1,
	"전문가": 1,
	"설계": 1,
	"아동을위한": 1,
	"훌륭": 1
}