{
	"Histórias": 1,
	"Mônica": 4,
	"vídeos": 2,
	"frequência": 1,
	"+": 12,
	"6": 3,
	"Coleções": 1,
	"40": 2,
	"episódios": 2,
	"—": 2,
	"EPISÓDIOS": 1,
	"GRÁTIS": 1,
	"atenção,": 1,
	"Atualização": 1,
	"crianças": 2,
	"São": 2,
	"diversão": 1,
	"família": 1,
	"Você": 1,
	"clássicos": 1,
	"histórias": 1,
	"é": 7,
	"serviço": 2,
	"dá": 1,
	"vídeos,": 1,
	"Preço": 2,
	"4": 1,
	"99": 2,
	"mês": 2,
	"lançamento:": 1,
	"2": 1,
	"válida": 2,
	"confirmação": 1,
	"renovação": 2,
	"automática": 1,
	"24": 4,
	"período": 3,
	"não": 2,
	"desistência": 1,
	"vigência": 1,
	"degustação,": 1,
	"será": 1,
	"Política": 1,
	"01": 2,
	"01digital.": 2,
	"만화": 3,
	"형식": 1,
	"모니카": 1,
	"클래스": 1,
	"스트립": 1,
	"언제": 2,
	"인터넷": 1,
	"다운로드": 2,
	"시청": 2,
	"가입": 3,
	"비디오": 3,
	"수신": 1,
	"주요": 1,
	"내용": 1,
	"+6": 1,
	"컬렉션": 1,
	"개": 3,
	"에피소드": 3,
	"무료": 1,
	"게임": 3,
	"주의력": 1,
	"시각적": 1,
	"인식": 1,
	"민첩성": 1,
	"테스트": 1,
	"지속적": 1,
	"업데이트": 1,
	"자동차": 1,
	"여행": 1,
	"대": 1,
	"식당": 1,
	"어린이": 1,
	"산만": 1,
	"것": 2,
	"적합한": 1,
	"인터페이스가있": 1,
	"환경": 1,
	"온라인": 1,
	"상태": 2,
	"수": 4,
	"번": 1,
	"구입": 1,
	"스마트": 1,
	"폰": 1,
	"태블릿": 1,
	"액세스": 2,
	"가족": 1,
	"모두를위한": 1,
	"수십": 1,
	"시간": 4,
	"재미": 1,
	"사랑": 1,
	"캐릭터": 1,
	"애니메이션": 1,
	"스토리": 1,
	"변형": 1,
	"만화책": 1,
	"고전적": 1,
	"스크립트": 1,
	"서명": 4,
	"최신": 1,
	"한": 3,
	"뉴스": 1,
	"완전": 1,
	"무제한": 1,
	"서비스": 2,
	"가격": 2,
	"달": 1,
	"4.99": 1,
	"달러": 2,
	"프로모션": 1,
	"월": 1,
	"2.99": 1,
	"귀하": 2,
	"계정": 3,
	"등록": 2,
	"기": 2,
	"유효": 3,
	"구매": 2,
	"확인시": 1,
	"결제": 1,
	"금액": 1,
	"청구": 2,
	"기간": 4,
	"종료": 1,
	"최소": 1,
	"전": 2,
	"자동": 2,
	"갱신": 3,
	"사용": 2,
	"중지": 1,
	"가치": 1,
	"환불": 1,
	"동안": 1,
	"인출시": 1,
	"중단": 3,
	"유료": 1,
	"구독": 1,
	"때": 1,
	"정보": 1,
	"보호": 1,
	"정책": 1,
	"자기": 1,
	"소개": 1,
	"디지털": 1,
	"게시": 1,
	"됨": 1
}{
	"Histórias": 1,
	"Mônica": 4,
	"vídeos": 2,
	"frequência": 1,
	"+": 12,
	"6": 3,
	"Coleções": 1,
	"40": 2,
	"episódios": 2,
	"—": 2,
	"EPISÓDIOS": 1,
	"GRÁTIS": 1,
	"atenção,": 1,
	"Atualização": 1,
	"crianças": 2,
	"São": 2,
	"diversão": 1,
	"família": 1,
	"Você": 1,
	"clássicos": 1,
	"histórias": 1,
	"é": 7,
	"serviço": 2,
	"dá": 1,
	"vídeos,": 1,
	"Preço": 2,
	"4": 1,
	"99": 2,
	"mês": 2,
	"lançamento:": 1,
	"2": 1,
	"válida": 2,
	"confirmação": 1,
	"renovação": 2,
	"automática": 1,
	"24": 4,
	"período": 3,
	"não": 2,
	"desistência": 1,
	"vigência": 1,
	"degustação,": 1,
	"será": 1,
	"Política": 1,
	"01": 2,
	"01digital.": 2,
	"만화": 3,
	"형식": 1,
	"모니카": 1,
	"클래스": 1,
	"스트립": 1,
	"언제": 2,
	"인터넷": 1,
	"다운로드": 2,
	"시청": 2,
	"가입": 3,
	"비디오": 3,
	"수신": 1,
	"주요": 1,
	"내용": 1,
	"+6": 1,
	"컬렉션": 1,
	"개": 3,
	"에피소드": 3,
	"무료": 1,
	"게임": 3,
	"주의력": 1,
	"시각적": 1,
	"인식": 1,
	"민첩성": 1,
	"테스트": 1,
	"지속적": 1,
	"업데이트": 1,
	"자동차": 1,
	"여행": 1,
	"대": 1,
	"식당": 1,
	"어린이": 1,
	"산만": 1,
	"것": 2,
	"적합한": 1,
	"인터페이스가있": 1,
	"환경": 1,
	"온라인": 1,
	"상태": 2,
	"수": 4,
	"번": 1,
	"구입": 1,
	"스마트": 1,
	"폰": 1,
	"태블릿": 1,
	"액세스": 2,
	"가족": 1,
	"모두를위한": 1,
	"수십": 1,
	"시간": 4,
	"재미": 1,
	"사랑": 1,
	"캐릭터": 1,
	"애니메이션": 1,
	"스토리": 1,
	"변형": 1,
	"만화책": 1,
	"고전적": 1,
	"스크립트": 1,
	"서명": 4,
	"최신": 1,
	"한": 3,
	"뉴스": 1,
	"완전": 1,
	"무제한": 1,
	"서비스": 2,
	"가격": 2,
	"달": 1,
	"4.99": 1,
	"달러": 2,
	"프로모션": 1,
	"월": 1,
	"2.99": 1,
	"귀하": 2,
	"계정": 3,
	"등록": 2,
	"기": 2,
	"유효": 3,
	"구매": 2,
	"확인시": 1,
	"결제": 1,
	"금액": 1,
	"청구": 2,
	"기간": 4,
	"종료": 1,
	"최소": 1,
	"전": 2,
	"자동": 2,
	"갱신": 3,
	"사용": 2,
	"중지": 1,
	"가치": 1,
	"환불": 1,
	"동안": 1,
	"인출시": 1,
	"중단": 3,
	"유료": 1,
	"구독": 1,
	"때": 1,
	"정보": 1,
	"보호": 1,
	"정책": 1,
	"자기": 1,
	"소개": 1,
	"디지털": 1,
	"게시": 1,
	"됨": 1
}