{
	"아이들": 3,
	"행복": 1,
	"웃음소리": 1,
	"베이비버스": 1,
	"▶어린": 1,
	"눈높이": 2,
	"반응형": 1,
	"인터랙티브": 1,
	"애니메이션": 1,
	"숫자공부": 2,
	"수": 2,
	"교육용": 1,
	"어플입니": 1,
	"▶키키": 1,
	"낚시": 1,
	"물고기": 1,
	"한마리": 1,
	"두마리": 1,
	"반복적": 2,
	"숫자세기": 2,
	"▶알": 1,
	"수집": 1,
	"채소": 1,
	"송아지": 1,
	"등": 2,
	"놀이": 3,
	"물건": 1,
	"마켓": 1,
	"진열대": 1,
	"배열한다음": 1,
	"장보기놀이": 1,
	"숫자": 1,
	"부모님들": 1,
	"관심": 1,
	"성장단계별": 1,
	"기초": 1,
	"지능발달": 1,
	"소통의사": 1,
	"창의력": 1,
	"예술감각": 1,
	"안전": 1,
	"환경보호,자연과학,올바른": 1,
	"습관": 1,
	"영역": 1,
	"내용": 1,
	"엄선": 1,
	"어린이": 2,
	"다양": 1,
	"주제": 1,
	"제작": 1,
	"단순": 1,
	"주입식학습": 1,
	"자연": 2,
	"문제해결능력": 1,
	"창의성": 1,
	"생활습관": 1,
	"사람": 1,
	"사랑": 1,
	"존중": 1,
	"인성": 1,
	"소유": 1,
	"성장": 1,
	"목적": 1,
	"지속적": 1,
	"외국어": 1,
	"추가": 1,
	"콘텐츠": 1,
	"업데이트": 1,
	"작업": 1,
	"진행": 1,
	"고객님": 1,
	"불편사항": 1,
	"문의사항": 1,
	"아래": 1,
	"주소": 1,
	"연락을주세요": 1,
	"▶커뮤니티": 1,
	"메일주소": 1,
	"페이스북": 1,
	"트위터:": 1,
	"홈페이지": 1
}