{
	"50th": 2,
	"the Moon": 1,
	"Landing with": 1,
	"NASA’s": 2,
	"1960s.": 1,
	"Channel’s": 2,
	"series, the “Apollo’s": 1,
	"Shot AR” app": 1,
	"•": 12,
	"the Lunar": 1,
	"Module of": 1,
	"11": 5,
	"the Moon,": 1,
	"authentic Apollo": 1,
	"11 spacesuit,": 1,
	"“Moon": 1,
	"Challenge”": 1,
	"to test": 1,
	"–": 2,
	"20": 2,
	"2019": 2,
	"missions, including": 1,
	"3D": 2,
	"Armstrong’s": 1,
	"“Apollo’s": 1,
	"”": 1,
	"달": 8,
	"착륙": 4,
	"50": 2,
	"주년": 2,
	"1960": 1,
	"년대": 1,
	"과감": 1,
	"우주": 4,
	"임무": 2,
	"행동": 1,
	"당신": 1,
	"위치": 1,
	"몰입": 2,
	"형": 2,
	"응용": 1,
	"프로그램": 1,
	"스미스": 2,
	"소": 2,
	"채널": 2,
	"획기적": 2,
	"6": 1,
	"부작": 1,
	"시리즈": 1,
	"AR\"앱": 1,
	"완벽": 1,
	"동반자": 1,
	"시대": 2,
	"시작": 1,
	"결정": 1,
	"이벤트": 1,
	"클로즈업": 1,
	"제공": 1,
	"무료": 1,
	"다운로드": 1,
	"우리": 1,
	"폭발": 1,
	"앱": 1,
	"특징": 1,
	"탐사": 1,
	"중반": 1,
	"자신": 1,
	"배치": 1,
	"자": 1,
	"만": 1,
	"토성": 1,
	"로켓": 1,
	"발사": 1,
	"아폴로": 3,
	"호": 1,
	"음력": 2,
	"명령": 2,
	"모듈": 2,
	"포털": 1,
	"몇": 1,
	"가지": 1,
	"흥미": 1,
	"진진": 1,
	"기능": 1,
	"경관": 1,
	"탐험": 1,
	"진정한": 1,
	"우주복": 2,
	"적합한": 1,
	"셀카": 1,
	"사회": 1,
	"친구들": 1,
	"공유": 1,
	"두": 1,
	"번": 1,
	"스릴": 1,
	"시뮬레이션": 1,
	"게임": 1,
	"사용": 1,
	"코스": 1,
	"탐색": 2,
	"크레이터": 1,
	"바위": 1,
	"수": 2,
	"테스트": 1,
	"년": 1,
	"7": 1,
	"월": 1,
	"일": 1,
	"기념": 1,
	"행사": 1,
	"역사적": 1,
	"시간별": 1,
	"업데이트": 1,
	"대화": 1,
	"타": 1,
	"라인": 1,
	"퀴즈": 1,
	"비디오": 1,
	"과거": 1,
	"현실": 1,
	"매혹적": 1,
	"사실": 1,
	"특별": 1,
	"역사": 1,
	"Neil": 1,
	"정통": 1,
	"스캔": 1,
	"포함": 1,
	"희귀": 1,
	"한": 1,
	"인공물": 1,
	"도구": 1,
	"접근": 1,
	"에피소드": 1,
	"독점": 1,
	"클립을보십시오": 1
}{
	"50th": 2,
	"the Moon": 1,
	"Landing with": 1,
	"NASA’s": 2,
	"1960s.": 1,
	"Channel’s": 2,
	"series, the “Apollo’s": 1,
	"Shot AR” app": 1,
	"•": 12,
	"the Lunar": 1,
	"Module of": 1,
	"11": 5,
	"the Moon,": 1,
	"authentic Apollo": 1,
	"11 spacesuit,": 1,
	"“Moon": 1,
	"Challenge”": 1,
	"to test": 1,
	"–": 2,
	"20": 2,
	"2019": 2,
	"missions, including": 1,
	"3D": 2,
	"Armstrong’s": 1,
	"“Apollo’s": 1,
	"”": 1,
	"달": 8,
	"착륙": 4,
	"50": 2,
	"주년": 2,
	"1960": 1,
	"년대": 1,
	"과감": 1,
	"우주": 4,
	"임무": 2,
	"행동": 1,
	"당신": 1,
	"위치": 1,
	"몰입": 2,
	"형": 2,
	"응용": 1,
	"프로그램": 1,
	"스미스": 2,
	"소": 2,
	"채널": 2,
	"획기적": 2,
	"6": 1,
	"부작": 1,
	"시리즈": 1,
	"AR\"앱": 1,
	"완벽": 1,
	"동반자": 1,
	"시대": 2,
	"시작": 1,
	"결정": 1,
	"이벤트": 1,
	"클로즈업": 1,
	"제공": 1,
	"무료": 1,
	"다운로드": 1,
	"우리": 1,
	"폭발": 1,
	"앱": 1,
	"특징": 1,
	"탐사": 1,
	"중반": 1,
	"자신": 1,
	"배치": 1,
	"자": 1,
	"만": 1,
	"토성": 1,
	"로켓": 1,
	"발사": 1,
	"아폴로": 3,
	"호": 1,
	"음력": 2,
	"명령": 2,
	"모듈": 2,
	"포털": 1,
	"몇": 1,
	"가지": 1,
	"흥미": 1,
	"진진": 1,
	"기능": 1,
	"경관": 1,
	"탐험": 1,
	"진정한": 1,
	"우주복": 2,
	"적합한": 1,
	"셀카": 1,
	"사회": 1,
	"친구들": 1,
	"공유": 1,
	"두": 1,
	"번": 1,
	"스릴": 1,
	"시뮬레이션": 1,
	"게임": 1,
	"사용": 1,
	"코스": 1,
	"탐색": 2,
	"크레이터": 1,
	"바위": 1,
	"수": 2,
	"테스트": 1,
	"년": 1,
	"7": 1,
	"월": 1,
	"일": 1,
	"기념": 1,
	"행사": 1,
	"역사적": 1,
	"시간별": 1,
	"업데이트": 1,
	"대화": 1,
	"타": 1,
	"라인": 1,
	"퀴즈": 1,
	"비디오": 1,
	"과거": 1,
	"현실": 1,
	"매혹적": 1,
	"사실": 1,
	"특별": 1,
	"역사": 1,
	"Neil": 1,
	"정통": 1,
	"스캔": 1,
	"포함": 1,
	"희귀": 1,
	"한": 1,
	"인공물": 1,
	"도구": 1,
	"접근": 1,
	"에피소드": 1,
	"독점": 1,
	"클립을보십시오": 1
}