{
	"수천": 1,
	"개": 1,
	"실제": 1,
	"예문": 1,
	"자막": 1,
	"이미지,": 1,
	"노래": 1,
	"기사": 1,
	"자신": 2,
	"맥락": 1,
	"단어": 1,
	"구성": 2,
	"요소": 2,
	"어원": 1,
	"완전": 1,
	"설명": 1,
	"자": 1,
	"이해": 1,
	"시간": 1,
	"진행": 1,
	"상황": 1,
	"추적": 1,
	"수준": 1,
	"적합한": 1,
	"콘텐츠": 1
}{
	"수천": 1,
	"개": 1,
	"실제": 1,
	"예문": 1,
	"자막": 1,
	"이미지,": 1,
	"노래": 1,
	"기사": 1,
	"자신": 2,
	"맥락": 1,
	"단어": 1,
	"구성": 2,
	"요소": 2,
	"어원": 1,
	"완전": 1,
	"설명": 1,
	"자": 1,
	"이해": 1,
	"시간": 1,
	"진행": 1,
	"상황": 1,
	"추적": 1,
	"수준": 1,
	"적합한": 1,
	"콘텐츠": 1
}