{
	"수백만": 1,
	"사용자": 1,
	"보유": 1,
	"수억": 1,
	"문제": 12,
	"해결": 4,
	"세계": 1,
	"제일": 1,
	"수학": 8,
	"해결사": 1,
	"기본": 1,
	"대수학": 4,
	"복잡": 1,
	"미적분": 3,
	"입력": 2,
	"카메라": 1,
	"답": 2,
	"수": 7,
	"세부적": 1,
	"풀": 1,
	"필요": 1,
	"휴대용": 1,
	"과외": 1,
	"선생님": 1,
	"어디": 1,
	"풀이": 2,
	"네트워크": 1,
	"연결": 1,
	"사용": 2,
	"다음": 1,
	"유형": 1,
	"기초": 1,
	"입문": 2,
	"삼각법": 1,
	"통계": 1,
	"선형": 1,
	"화학": 1,
	"그래프": 1,
	"효율적": 1,
	"고등학생": 1,
	"대학생": 1,
	"야후": 1,
	"뉴스": 1,
	"툴": 2,
	"도달": 1,
	"과정": 1,
	"무엇": 1,
	"앱은": 1,
	"숙제하": 1,
	"데": 1,
	"도움": 1,
	"과제": 1,
	"대": 1,
	"뿐": 1,
	"방법": 1,
	"엔터": 1,
	"키": 1
}{
	"수백만": 1,
	"사용자": 1,
	"보유": 1,
	"수억": 1,
	"문제": 12,
	"해결": 4,
	"세계": 1,
	"제일": 1,
	"수학": 8,
	"해결사": 1,
	"기본": 1,
	"대수학": 4,
	"복잡": 1,
	"미적분": 3,
	"입력": 2,
	"카메라": 1,
	"답": 2,
	"수": 7,
	"세부적": 1,
	"풀": 1,
	"필요": 1,
	"휴대용": 1,
	"과외": 1,
	"선생님": 1,
	"어디": 1,
	"풀이": 2,
	"네트워크": 1,
	"연결": 1,
	"사용": 2,
	"다음": 1,
	"유형": 1,
	"기초": 1,
	"입문": 2,
	"삼각법": 1,
	"통계": 1,
	"선형": 1,
	"화학": 1,
	"그래프": 1,
	"효율적": 1,
	"고등학생": 1,
	"대학생": 1,
	"야후": 1,
	"뉴스": 1,
	"툴": 2,
	"도달": 1,
	"과정": 1,
	"무엇": 1,
	"앱은": 1,
	"숙제하": 1,
	"데": 1,
	"도움": 1,
	"과제": 1,
	"대": 1,
	"뿐": 1,
	"방법": 1,
	"엔터": 1,
	"키": 1
}