{
	"It’s": 1,
	"트랜스퍼": 1,
	"차량": 1,
	"국제": 1,
	"우주": 1,
	"정거장": 1,
	"성공적": 1,
	"선적되도록하": 1,
	"것": 2,
	"귀하": 1,
	"임무": 1,
	"중력": 3,
	"효과": 1,
	"경험": 1,
	"작업": 2,
	"수행": 1,
	"수": 2,
	"제": 1,
	"이동": 1,
	"시": 1,
	"지구": 1,
	"익숙": 1,
	"주변": 1,
	"시간": 1,
	"도움을줍니": 1,
	"그러나주의하십시오,": 1,
	"당신": 1,
	"완료를위한": 1,
	"미션": 1,
	"패치": 1,
	"수집": 1,
	"영향": 2,
	"방지": 1,
	"발견을하십시오": 1,
	"응용": 1,
	"프로그램": 1,
	"교": 1,
	"가정": 1,
	"사용": 1,
	"인체": 1,
	"정보": 1,
	"포함": 1
}{
	"It’s": 1,
	"트랜스퍼": 1,
	"차량": 1,
	"국제": 1,
	"우주": 1,
	"정거장": 1,
	"성공적": 1,
	"선적되도록하": 1,
	"것": 2,
	"귀하": 1,
	"임무": 1,
	"중력": 3,
	"효과": 1,
	"경험": 1,
	"작업": 2,
	"수행": 1,
	"수": 2,
	"제": 1,
	"이동": 1,
	"시": 1,
	"지구": 1,
	"익숙": 1,
	"주변": 1,
	"시간": 1,
	"도움을줍니": 1,
	"그러나주의하십시오,": 1,
	"당신": 1,
	"완료를위한": 1,
	"미션": 1,
	"패치": 1,
	"수집": 1,
	"영향": 2,
	"방지": 1,
	"발견을하십시오": 1,
	"응용": 1,
	"프로그램": 1,
	"교": 1,
	"가정": 1,
	"사용": 1,
	"인체": 1,
	"정보": 1,
	"포함": 1
}