{
	"100+": 1,
	"102": 4,
	"52": 8,
	"2": 2,
	"50": 8,
	"knot’s": 1,
	"28": 2,
	"11": 2,
	"Surgeon’s": 2,
	"9": 2,
	"27": 2,
	"Trucker’s": 1,
	"13": 2,
	"Fisherman’s": 1,
	"10": 2,
	"–": 1,
	"(800,000+": 1,
	"100": 1,
	"+": 2,
	"매듭": 91,
	"프로": 2,
	"신뢰": 2,
	"​​세계": 1,
	"최고": 5,
	"판매": 3,
	"인쇄": 1,
	"참조": 3,
	"노트": 5,
	"애니메이션": 4,
	"둘": 1,
	"앱": 2,
	"학습": 1,
	"낚시": 8,
	"곳": 1,
	"응용": 1,
	"프로그램": 1,
	"대부분": 2,
	"비상": 2,
	"바늘": 2,
	"제거": 3,
	"기술": 2,
	"로프": 7,
	"각각": 1,
	"자신": 2,
	"비디오": 1,
	"완성": 2,
	"단계": 6,
	"그림": 3,
	"및": 1,
	"설명": 3,
	"사용": 1,
	"수": 3,
	"상점에있는": 1,
	"카드": 1,
	"이동": 2,
	"가능한": 1,
	"다음": 2,
	"포함": 2,
	"터미널": 1,
	"태클": 1,
	"연결": 1,
	"아버": 1,
	"바하": 1,
	"버클리": 1,
	"끈목": 1,
	"센타": 1,
	"우": 1,
	"루스": 1,
	"데비": 1,
	"드롭": 1,
	"샷": 1,
	"리그": 1,
	"계란": 1,
	"루프": 10,
	"전쟁": 2,
	"승자": 2,
	"물고기": 2,
	"바보": 1,
	"하비": 1,
	"드라이": 1,
	"플라이": 1,
	"향상": 1,
	"것": 3,
	"클린치": 1,
	"특별": 2,
	"비": 3,
	"모노": 2,
	"해외": 1,
	"회전": 1,
	"오비스": 1,
	"팔": 1,
	"의": 2,
	"리플": 1,
	"히치": 16,
	"샌디에": 1,
	"스넬": 2,
	"전통적": 1,
	"버전": 3,
	"유": 3,
	"세계": 3,
	"박람회": 1,
	"라": 6,
	"올브라이트": 1,
	"혈액": 1,
	"브리스톨": 1,
	"일명": 1,
	"이름": 2,
	"더블": 2,
	"네일": 1,
	"탄화": 1,
	"슬림": 1,
	"뷰티": 1,
	"독점": 1,
	"지도": 1,
	"외과": 2,
	"의사": 1,
	"윌리스": 1,
	"유카탄": 1,
	"트위스트": 1,
	"호머로드": 1,
	"킹": 1,
	"슬링": 1,
	"슬립": 2,
	"퍼펙션": 1,
	"스파이": 1,
	"끝": 2,
	"플러스": 1,
	"찌": 1,
	"스토퍼": 2,
	"도구": 1,
	"네": 1,
	"두": 6,
	"​​개": 2,
	"스트라이크": 1,
	"표시": 1,
	"훅": 1,
	"기법": 1,
	"객체": 1,
	"밧줄": 2,
	"앵커": 1,
	"벤드": 5,
	"블레이크": 1,
	"히​​치": 1,
	"클리트": 1,
	"정향": 1,
	"암소": 1,
	"말초": 1,
	"둘레": 1,
	"하프": 2,
	"개": 2,
	"마": 1,
	"계류": 1,
	"말뚝": 1,
	"연결부": 1,
	"롤링": 2,
	"슈베": 1,
	"미끄": 3,
	"중간": 1,
	"목재": 1,
	"차질": 1,
	"트럭": 1,
	"운전사": 1,
	"굴곡": 1,
	"백업": 1,
	"나": 1,
	"활": 1,
	"일반적": 1,
	"휘핑": 1,
	"캐릭": 1,
	"어부": 1,
	"번": 1,
	"히빙": 1,
	"원숭이": 1,
	"주먹": 1,
	"양": 1,
	"정강이": 1,
	"시트": 1,
	"도": 1,
	"두배": 1,
	"스퀘어": 1,
	"(리프": 1,
	"제플린": 1,
	"하천": 1,
	"만곡부": 1,
	"나비": 1,
	"8": 1,
	"혼다": 1,
	"여덟": 1,
	"요세미티": 1,
	"제품": 1,
	"특징": 1,
	"800,000": 1,
	"책": 1,
	"삽화": 1,
	"카테고리별": 1,
	"나열": 1,
	"검색": 1,
	"알파벳순": 1,
	"개요": 1,
	"페이지": 3,
	"제공": 2,
	"단계별": 1,
	"스크린": 1,
	"각": 1,
	"별도": 1,
	"방향": 1,
	"와이프": 1,
	"​​이미지": 1,
	"앞": 1,
	"뒤": 1,
	"영​​화": 1,
	"마음": 1,
	"목록": 1,
	"저장": 1,
	"용어": 2,
	"​​존경": 1,
	"게": 1,
	"중": 1,
	"하나": 1,
	"우리": 2,
	"의견": 2,
	"제안": 1,
	"요청": 1,
	"이메일": 1,
	"자유": 1,
	"여러분": 1,
	"사랑해": 1
}{
	"100+": 1,
	"102": 4,
	"52": 8,
	"2": 2,
	"50": 8,
	"knot’s": 1,
	"28": 2,
	"11": 2,
	"Surgeon’s": 2,
	"9": 2,
	"27": 2,
	"Trucker’s": 1,
	"13": 2,
	"Fisherman’s": 1,
	"10": 2,
	"–": 1,
	"(800,000+": 1,
	"100": 1,
	"+": 2,
	"매듭": 91,
	"프로": 2,
	"신뢰": 2,
	"​​세계": 1,
	"최고": 5,
	"판매": 3,
	"인쇄": 1,
	"참조": 3,
	"노트": 5,
	"애니메이션": 4,
	"둘": 1,
	"앱": 2,
	"학습": 1,
	"낚시": 8,
	"곳": 1,
	"응용": 1,
	"프로그램": 1,
	"대부분": 2,
	"비상": 2,
	"바늘": 2,
	"제거": 3,
	"기술": 2,
	"로프": 7,
	"각각": 1,
	"자신": 2,
	"비디오": 1,
	"완성": 2,
	"단계": 6,
	"그림": 3,
	"및": 1,
	"설명": 3,
	"사용": 1,
	"수": 3,
	"상점에있는": 1,
	"카드": 1,
	"이동": 2,
	"가능한": 1,
	"다음": 2,
	"포함": 2,
	"터미널": 1,
	"태클": 1,
	"연결": 1,
	"아버": 1,
	"바하": 1,
	"버클리": 1,
	"끈목": 1,
	"센타": 1,
	"우": 1,
	"루스": 1,
	"데비": 1,
	"드롭": 1,
	"샷": 1,
	"리그": 1,
	"계란": 1,
	"루프": 10,
	"전쟁": 2,
	"승자": 2,
	"물고기": 2,
	"바보": 1,
	"하비": 1,
	"드라이": 1,
	"플라이": 1,
	"향상": 1,
	"것": 3,
	"클린치": 1,
	"특별": 2,
	"비": 3,
	"모노": 2,
	"해외": 1,
	"회전": 1,
	"오비스": 1,
	"팔": 1,
	"의": 2,
	"리플": 1,
	"히치": 16,
	"샌디에": 1,
	"스넬": 2,
	"전통적": 1,
	"버전": 3,
	"유": 3,
	"세계": 3,
	"박람회": 1,
	"라": 6,
	"올브라이트": 1,
	"혈액": 1,
	"브리스톨": 1,
	"일명": 1,
	"이름": 2,
	"더블": 2,
	"네일": 1,
	"탄화": 1,
	"슬림": 1,
	"뷰티": 1,
	"독점": 1,
	"지도": 1,
	"외과": 2,
	"의사": 1,
	"윌리스": 1,
	"유카탄": 1,
	"트위스트": 1,
	"호머로드": 1,
	"킹": 1,
	"슬링": 1,
	"슬립": 2,
	"퍼펙션": 1,
	"스파이": 1,
	"끝": 2,
	"플러스": 1,
	"찌": 1,
	"스토퍼": 2,
	"도구": 1,
	"네": 1,
	"두": 6,
	"​​개": 2,
	"스트라이크": 1,
	"표시": 1,
	"훅": 1,
	"기법": 1,
	"객체": 1,
	"밧줄": 2,
	"앵커": 1,
	"벤드": 5,
	"블레이크": 1,
	"히​​치": 1,
	"클리트": 1,
	"정향": 1,
	"암소": 1,
	"말초": 1,
	"둘레": 1,
	"하프": 2,
	"개": 2,
	"마": 1,
	"계류": 1,
	"말뚝": 1,
	"연결부": 1,
	"롤링": 2,
	"슈베": 1,
	"미끄": 3,
	"중간": 1,
	"목재": 1,
	"차질": 1,
	"트럭": 1,
	"운전사": 1,
	"굴곡": 1,
	"백업": 1,
	"나": 1,
	"활": 1,
	"일반적": 1,
	"휘핑": 1,
	"캐릭": 1,
	"어부": 1,
	"번": 1,
	"히빙": 1,
	"원숭이": 1,
	"주먹": 1,
	"양": 1,
	"정강이": 1,
	"시트": 1,
	"도": 1,
	"두배": 1,
	"스퀘어": 1,
	"(리프": 1,
	"제플린": 1,
	"하천": 1,
	"만곡부": 1,
	"나비": 1,
	"8": 1,
	"혼다": 1,
	"여덟": 1,
	"요세미티": 1,
	"제품": 1,
	"특징": 1,
	"800,000": 1,
	"책": 1,
	"삽화": 1,
	"카테고리별": 1,
	"나열": 1,
	"검색": 1,
	"알파벳순": 1,
	"개요": 1,
	"페이지": 3,
	"제공": 2,
	"단계별": 1,
	"스크린": 1,
	"각": 1,
	"별도": 1,
	"방향": 1,
	"와이프": 1,
	"​​이미지": 1,
	"앞": 1,
	"뒤": 1,
	"영​​화": 1,
	"마음": 1,
	"목록": 1,
	"저장": 1,
	"용어": 2,
	"​​존경": 1,
	"게": 1,
	"중": 1,
	"하나": 1,
	"우리": 2,
	"의견": 2,
	"제안": 1,
	"요청": 1,
	"이메일": 1,
	"자유": 1,
	"여러분": 1,
	"사랑해": 1
}