{
	"A300CS,": 1,
	"i750TC,": 2,
	"4.0": 2,
	"안드로이드": 1,
	"응용": 2,
	"프로그램": 2,
	"최고": 1,
	"완전": 1,
	"기능": 4,
	"다이빙": 24,
	"로그": 1,
	"공식": 1,
	"앱이며,": 1,
	"다음": 1,
	"제조업체": 1,
	"생산": 1,
	"컴퓨터": 2,
	"데이터": 5,
	"지원": 2,
	"수중": 1,
	"호흡기": 1,
	"해양": 1,
	"홀리스,": 1,
	"서브": 1,
	"기": 1,
	"부샤": 1,
	"풍모": 1,
	"보": 4,
	"편집": 3,
	"세부": 2,
	"관리": 6,
	"검색": 4,
	"위치": 4,
	"형": 1,
	"친구": 3,
	"기반": 1,
	"편집하": 2,
	"명소": 1,
	"장비": 3,
	"연락처": 1,
	"가능한": 1,
	"애플리케이션": 1,
	"의료": 3,
	"인증": 3,
	"정보": 8,
	"포함": 3,
	"개": 3,
	"추적": 2,
	"유튜브": 1,
	"동영상": 1,
	"링크": 1,
	"사진": 1,
	"추가": 2,
	"시간": 1,
	"기억": 1,
	"사회": 1,
	"공유": 1,
	"온라인": 2,
	"저장": 1,
	"장치": 2,
	"동기화": 2,
	"다운로드": 1,
	"설정": 1,
	"업로드": 1,
	"블루투스": 3,
	"스마트": 1,
	"(A300CS": 1,
	"사용": 5,
	"수": 7,
	"펌웨어": 1,
	"업데이트합니": 1,
	"필요": 1,
	"개요": 1,
	"당신이보고,": 1,
	"​​있습니": 2,
	"섹션": 1,
	"사이트": 3,
	"탱크": 1,
	"버디": 1,
	"가방": 1,
	"등": 1,
	"필요한": 1,
	"제공": 2,
	"손": 1,
	"유": 1,
	"전체": 1,
	"화면보": 1,
	"프로필": 1,
	"추": 1,
	"입력": 1,
	"폼": 1,
	"당신": 8,
	"한": 1,
	"방법": 1,
	"세계": 1,
	"우리": 2,
	"활동지도": 1,
	"전화": 1,
	"고유": 1,
	"다이빙하": 1,
	"어디": 1,
	"이": 1,
	"백업": 1,
	"시스템": 1,
	"포럼": 1,
	"게시": 1,
	"개발자들": 1,
	"연결": 1,
	"이메일": 1,
	"문의": 1,
	"웹": 1,
	"방문": 1
}{
	"A300CS,": 1,
	"i750TC,": 2,
	"4.0": 2,
	"안드로이드": 1,
	"응용": 2,
	"프로그램": 2,
	"최고": 1,
	"완전": 1,
	"기능": 4,
	"다이빙": 24,
	"로그": 1,
	"공식": 1,
	"앱이며,": 1,
	"다음": 1,
	"제조업체": 1,
	"생산": 1,
	"컴퓨터": 2,
	"데이터": 5,
	"지원": 2,
	"수중": 1,
	"호흡기": 1,
	"해양": 1,
	"홀리스,": 1,
	"서브": 1,
	"기": 1,
	"부샤": 1,
	"풍모": 1,
	"보": 4,
	"편집": 3,
	"세부": 2,
	"관리": 6,
	"검색": 4,
	"위치": 4,
	"형": 1,
	"친구": 3,
	"기반": 1,
	"편집하": 2,
	"명소": 1,
	"장비": 3,
	"연락처": 1,
	"가능한": 1,
	"애플리케이션": 1,
	"의료": 3,
	"인증": 3,
	"정보": 8,
	"포함": 3,
	"개": 3,
	"추적": 2,
	"유튜브": 1,
	"동영상": 1,
	"링크": 1,
	"사진": 1,
	"추가": 2,
	"시간": 1,
	"기억": 1,
	"사회": 1,
	"공유": 1,
	"온라인": 2,
	"저장": 1,
	"장치": 2,
	"동기화": 2,
	"다운로드": 1,
	"설정": 1,
	"업로드": 1,
	"블루투스": 3,
	"스마트": 1,
	"(A300CS": 1,
	"사용": 5,
	"수": 7,
	"펌웨어": 1,
	"업데이트합니": 1,
	"필요": 1,
	"개요": 1,
	"당신이보고,": 1,
	"​​있습니": 2,
	"섹션": 1,
	"사이트": 3,
	"탱크": 1,
	"버디": 1,
	"가방": 1,
	"등": 1,
	"필요한": 1,
	"제공": 2,
	"손": 1,
	"유": 1,
	"전체": 1,
	"화면보": 1,
	"프로필": 1,
	"추": 1,
	"입력": 1,
	"폼": 1,
	"당신": 8,
	"한": 1,
	"방법": 1,
	"세계": 1,
	"우리": 2,
	"활동지도": 1,
	"전화": 1,
	"고유": 1,
	"다이빙하": 1,
	"어디": 1,
	"이": 1,
	"백업": 1,
	"시스템": 1,
	"포럼": 1,
	"게시": 1,
	"개발자들": 1,
	"연결": 1,
	"이메일": 1,
	"문의": 1,
	"웹": 1,
	"방문": 1
}