{
	"&": 2,
	"2019": 2,
	"응용": 2,
	"프로그램": 1,
	"당신": 2,
	"마을": 2,
	"희귀": 1,
	"카드": 3,
	"세트": 1,
	"무료": 29,
	"제공": 3,
	"것": 2,
	"이것": 2,
	"사용": 1,
	"가슴": 1,
	"수": 2,
	"동전": 18,
	"스핀": 22,
	"업데이트": 3,
	"보상": 3,
	"바이킹": 1,
	"건설": 1,
	"여분": 1,
	"장소": 1,
	"우리": 1,
	"시간": 1,
	"절약": 1,
	"곳": 2,
	"일": 9,
	"다운로드": 1,
	"보너스": 3,
	"보물": 1,
	"앱": 1,
	"확인": 1,
	"최고": 1,
	"링크": 20,
	"풍모": 1,
	"자유": 1,
	"회전": 1,
	"선물": 2,
	"게임": 2,
	"경량": 1,
	"설계": 1,
	"사용자": 2,
	"친화적": 1,
	"인터페이스": 1,
	"커뮤니케이션": 1,
	"댓글": 1,
	"한": 1,
	"코": 2,
	"마스터": 1,
	"대가": 1,
	"주인": 1,
	"발생기": 1,
	"코드": 1,
	"슬롯": 1
}{
	"&": 2,
	"2019": 2,
	"응용": 2,
	"프로그램": 1,
	"당신": 2,
	"마을": 2,
	"희귀": 1,
	"카드": 3,
	"세트": 1,
	"무료": 29,
	"제공": 3,
	"것": 2,
	"이것": 2,
	"사용": 1,
	"가슴": 1,
	"수": 2,
	"동전": 18,
	"스핀": 22,
	"업데이트": 3,
	"보상": 3,
	"바이킹": 1,
	"건설": 1,
	"여분": 1,
	"장소": 1,
	"우리": 1,
	"시간": 1,
	"절약": 1,
	"곳": 2,
	"일": 9,
	"다운로드": 1,
	"보너스": 3,
	"보물": 1,
	"앱": 1,
	"확인": 1,
	"최고": 1,
	"링크": 20,
	"풍모": 1,
	"자유": 1,
	"회전": 1,
	"선물": 2,
	"게임": 2,
	"경량": 1,
	"설계": 1,
	"사용자": 2,
	"친화적": 1,
	"인터페이스": 1,
	"커뮤니케이션": 1,
	"댓글": 1,
	"한": 1,
	"코": 2,
	"마스터": 1,
	"대가": 1,
	"주인": 1,
	"발생기": 1,
	"코드": 1,
	"슬롯": 1
}