{
	"★": 16,
	"100": 2,
	"2": 2,
	"그것": 1,
	"아케이드": 1,
	"스타일": 1,
	"농구": 2,
	"촬영": 1,
	"사람들": 1,
	"덩크": 1,
	"크로스": 1,
	"오버": 1,
	"스텝": 1,
	"​​백": 1,
	"토너먼트": 1,
	"국가": 1,
	"여행": 1,
	"가지": 1,
	"이상": 1,
	"독특": 1,
	"코트": 1,
	"온라인": 1,
	"라이브": 1,
	"이벤트": 1,
	"경쟁": 1,
	"귀하": 1,
	"모양": 1,
	"사용자": 1,
	"정의": 1,
	"수": 1,
	"업그레": 1,
	"드하십시오": 1,
	"화": 1,
	"화면": 1,
	"도전": 1,
	"모두": 1,
	"스포츠": 1,
	"게임": 1,
	"팀원": 1,
	"청구": 1,
	"다운로드": 1
}{
	"★": 16,
	"100": 2,
	"2": 2,
	"그것": 1,
	"아케이드": 1,
	"스타일": 1,
	"농구": 2,
	"촬영": 1,
	"사람들": 1,
	"덩크": 1,
	"크로스": 1,
	"오버": 1,
	"스텝": 1,
	"​​백": 1,
	"토너먼트": 1,
	"국가": 1,
	"여행": 1,
	"가지": 1,
	"이상": 1,
	"독특": 1,
	"코트": 1,
	"온라인": 1,
	"라이브": 1,
	"이벤트": 1,
	"경쟁": 1,
	"귀하": 1,
	"모양": 1,
	"사용자": 1,
	"정의": 1,
	"수": 1,
	"업그레": 1,
	"드하십시오": 1,
	"화": 1,
	"화면": 1,
	"도전": 1,
	"모두": 1,
	"스포츠": 1,
	"게임": 1,
	"팀원": 1,
	"청구": 1,
	"다운로드": 1
}