{
	"3D": 4,
	"9": 8,
	"볼링": 1,
	"농구": 1,
	"저격": 1,
	"손가락": 1,
	"끝": 1,
	"축구": 1,
	"스케": 1,
	"홉볼,": 1,
	"롤러": 6,
	"배드민턴": 1,
	"핀볼,": 1,
	"킹": 1,
	"테이블": 1,
	"하키": 1,
	"오토바이": 1,
	"기타": 1,
	"스포츠": 1,
	"게임": 8,
	"좋아한다면": 1,
	"볼": 2,
	"실제": 1,
	"육체적": 1,
	"중독성": 1,
	"효과": 1,
	"공": 9,
	"스타": 1,
	"기반": 1,
	"이동": 1,
	"방향": 4,
	"완료": 2,
	"휴대폰": 1,
	"상금": 1,
	"구멍": 6,
	"휴대": 1,
	"전화": 1,
	"화면": 3,
	"슬라이드": 1,
	"태스크": 1,
	"레벨": 1,
	"모드": 5,
	"자": 1,
	"만": 1,
	"도전": 3,
	"욕구": 1,
	"충족": 1,
	"단계": 1,
	"통": 2,
	"수": 7,
	"있는지보십시오": 1,
	"정보": 1,
	"간단한": 1,
	"조작": 1,
	"슬라이딩": 1,
	"목표": 1,
	"힘": 1,
	"매개": 1,
	"변수": 1,
	"조정": 2,
	"자신": 1,
	"감정": 1,
	"인터페이스": 1,
	"설정": 1,
	"전화기": 1,
	"클래식": 2,
	"놀": 1,
	"분수": 1,
	"무작위": 1,
	"깜박": 1,
	"특별": 1,
	"보상": 4,
	"동반": 1,
	"조준": 1,
	"비": 1,
	"대응": 1,
	"점수": 2,
	"현재": 1,
	"비율": 1,
	"곱": 1,
	"해당": 3,
	"추": 2,
	"경우": 2,
	"1": 1,
	"개": 2,
	"보너스": 1,
	"티켓": 1,
	"포함": 1,
	"작업": 3,
	"미션": 1,
	"다음": 1,
	"임무": 1,
	"전달": 1,
	"특징": 1,
	"-": 3,
	"플레이": 2,
	"타격": 1,
	"현실적": 1,
	"장면": 1,
	"신체적": 1,
	"경험": 1,
	"피부": 1,
	"당신": 2,
	"자길": 1,
	"롤링": 1,
	"스카이": 1,
	"점수를내": 1,
	"기술": 1,
	"콤보": 1,
	"우리": 4,
	"지원": 1,
	"다섯": 1,
	"칭찬을주세요,": 1,
	"일할": 1,
	"것": 3,
	"게임이": 1,
	"계속해서": 1,
	"집중": 1,
	"질문": 1,
	"이메일": 1,
	"가능": 1,
	"한": 1,
	"해결": 1,
	"감사": 1
}