{
	"전": 3,
	"세계": 4,
	"축구": 7,
	"소식": 3,
	"어디": 1,
	"팀": 7,
	"경기": 5,
	"팬": 2,
	"필수적": 1,
	"앱입니": 2,
	"200개": 3,
	"이상": 2,
	"리그": 5,
	"대회": 3,
	"사용자": 1,
	"필요": 1,
	"뉴스": 8,
	"스트림": 2,
	"커스터마이징": 1,
	"수": 10,
	"등": 4,
	"선호": 1,
	"최적": 1,
	"관심": 1,
	"문제": 2,
	"포함": 1,
	"라이브": 4,
	"보도": 2,
	"대표적": 1,
	"전문": 1,
	"분석": 2,
	"확인": 2,
	"매치": 1,
	"결과": 1,
	"예측": 1,
	"최우수": 1,
	"투표": 1,
	"참가": 1,
	"즉각적": 2,
	"푸시": 4,
	"활성": 2,
	"라이브스코어": 1,
	"이적": 2,
	"정보": 3,
	"신속한": 1,
	"속보": 1,
	"최초": 1,
	"하이라이트": 1,
	"커스터마이징하": 1,
	"선택": 1,
	"대": 1,
	"활성화": 1,
	"만큼": 1,
	"팔로우하시": 1,
	"뉴스룸": 1,
	"선정": 1,
	"관련": 1,
	"전후": 1,
	"루머": 1,
	"클럽": 2,
	"페이지": 1,
	"팔로우하": 1,
	"최신": 1,
	"시즌": 1,
	"스탯": 1,
	"대회별": 1,
	"앱": 1,
	"사용": 1,
	"피드백": 1,
	"아래": 1,
	"방법": 1,
	"이메일:": 1
}