{
	"BB’s": 1,
	"20": 1,
	"1100": 1,
	"don’t": 1,
	"It’s": 1,
	"out’s,": 1,
	"–": 2,
	"펠렛": 1,
	"에어": 1,
	"소프트": 1,
	"궁도": 1,
	"페인트": 1,
	"볼": 1,
	"탄도": 1,
	"애플": 1,
	"리케이션": 1,
	"스웨덴": 1,
	"사": 1,
	"최초": 1,
	"포켓": 1,
	"레이더": 2,
	"탄": 1,
	"크로노": 2,
	"그래프": 2,
	"사용": 5,
	"20fps": 1,
	"1100fps까지": 1,
	"데이터": 5,
	"기록": 3,
	"수": 6,
	"적": 1,
	"펠릿,": 1,
	"속도": 1,
	"싶다면": 1,
	"응용": 1,
	"프로그램": 1,
	"테스트": 2,
	"조정": 2,
	"프로필": 3,
	"저장": 2,
	"샷": 4,
	"음성": 2,
	"범위": 3,
	"대상": 1,
	"그룹화": 1,
	"가능": 3,
	"결과": 1,
	"표적": 1,
	"눈": 1,
	"추": 1,
	"평가": 1,
	"문자열": 2,
	"기능": 2,
	"일": 1,
	"힘": 2,
	"확인": 2,
	"주머니": 1,
	"블루투스": 1,
	"시작": 2,
	"휴대": 1,
	"전화": 1,
	"앱": 2,
	"것": 2,
	"그룹": 1,
	"초기화": 1,
	"촬영": 1,
	"자신": 1,
	"포함": 1,
	"실시간": 1,
	"표시": 1,
	"지우기": 1,
	"오디오": 1,
	"소리": 1,
	"전환": 1,
	"설정": 2,
	"기억": 1,
	"속": 1,
	"선택": 1,
	"입력": 2,
	"향후": 1,
	"개발": 2,
	"용": 2,
	"프로파": 1,
	"다중": 1,
	"단위": 1,
	"판독": 1,
	"값": 1,
	"감도": 1,
	"리턴": 1,
	"카운트": 1,
	"클립": 1,
	"보드": 1,
	"버전": 1,
	"업데이트": 1,
	"등록": 1,
	"웹": 2,
	"사이트": 2,
	"안내": 1,
	"내": 1,
	"링크": 1,
	"허가": 1,
	"딜러": 1,
	"구입": 1,
	"자세한": 1,
	"내용": 1,
	"참조": 1
}